kevlar_system_inspector/__init__.py
kevlar_system_inspector/__main__.py
kevlar_system_inspector/conftest.py
kevlar_system_inspector/console.py
kevlar_system_inspector/decorators.py
kevlar_system_inspector/output.py
kevlar_system_inspector/report.py
kevlar_system_inspector/sysinfo.py
kevlar_system_inspector/test_allowlisting.py
kevlar_system_inspector/test_kernel_config.py
kevlar_system_inspector/test_kernel_sandboxing.py
kevlar_system_inspector/test_offline_integrity.py
kevlar_system_inspector/test_secure_networking.py
kevlar_system_inspector/test_systemd_syscall_filtering.py
kevlar_system_inspector/version.py
kevlar_system_inspector/resources/__init__.py
kevlar_system_inspector/templates/__init__.py
kevlar_system_inspector/templates/failures.rst
kevlar_system_inspector/templates/html5-template.txt
kevlar_system_inspector/templates/report.rst
kevlar_system_inspector/templates/starlab.css
kevlar_system_inspector/templates/successes.rst
kevlar_system_inspector/templates/summary.rst
kevlar_system_inspector/templates/warnings.rst
kevlar_system_inspector/utils/__init__.py
kevlar_system_inspector/utils/access.py
kevlar_system_inspector/utils/elf.py
kevlar_system_inspector/utils/kconfig.py
kevlar_system_inspector/utils/modules.py
kevlar_system_inspector/utils/mount.py
kevlar_system_inspector/utils/systemd.py
kevlar_system_inspector/utils/workdir.py
kevlar_system_inspector-1.1.1.data/scripts/kevlar-system-inspector
kevlar_system_inspector-1.1.1.dist-info/LICENSE
kevlar_system_inspector-1.1.1.dist-info/METADATA
kevlar_system_inspector-1.1.1.dist-info/WHEEL
kevlar_system_inspector-1.1.1.dist-info/top_level.txt
kevlar_system_inspector-1.1.1.dist-info/RECORD
