Metadata-Version: 2.1
Name: kevlar-system-inspector
Version: 1.1.1
Summary: A security scanner for Linux systems
Home-page: https://www.starlab.io/explore-kevlar-system-inspector
Author: Star Lab
Author-email: info@starlab.io
License: MIT
Classifier: Development Status :: 5 - Production/Stable
Classifier: Environment :: Console
Classifier: Intended Audience :: Developers
Classifier: Intended Audience :: Information Technology
Classifier: License :: OSI Approved :: MIT License
Classifier: Operating System :: POSIX :: Linux
Classifier: Programming Language :: Python :: 3
Classifier: Programming Language :: Python :: 3 :: Only
Classifier: Topic :: Security
Classifier: Topic :: Software Development :: Embedded Systems
Classifier: Topic :: Software Development :: Quality Assurance
Classifier: Topic :: Software Development :: Testing
Classifier: Topic :: System :: Systems Administration
Classifier: Topic :: Utilities
Requires-Python: >=3.7
License-File: LICENSE
Requires-Dist: pytest >=6.2
Requires-Dist: rich
Requires-Dist: docutils
Requires-Dist: jinja2 >=2.11
Requires-Dist: pyelftools
Provides-Extra: test
Requires-Dist: black >=22.0 ; extra == 'test'
Requires-Dist: flake8 >=5.0 ; extra == 'test'
Requires-Dist: mypy ==1.0 ; extra == 'test'
Requires-Dist: pytest-cov >=4.0 ; extra == 'test'
